MANIFEST.in
setup.cfg
setup.py
src/xmlsec.h
src/xmlsec/__init__.py
src/xmlsec/constants.pxd
src/xmlsec/constants.pyx
src/xmlsec/ds.pxd
src/xmlsec/ds.pyx
src/xmlsec/enc.pxd
src/xmlsec/enc.pyx
src/xmlsec/error.py
src/xmlsec/key.pxd
src/xmlsec/key.pyx
src/xmlsec/meta.py
src/xmlsec/ssl.pxd
src/xmlsec/template.pxd
src/xmlsec/template.pyx
src/xmlsec/tree.pxd
src/xmlsec/tree.pyx
src/xmlsec/utils.pxd
src/xmlsec/utils.pyx
xmlsec_aop.egg-info/PKG-INFO
xmlsec_aop.egg-info/SOURCES.txt
xmlsec_aop.egg-info/dependency_links.txt
xmlsec_aop.egg-info/requires.txt
xmlsec_aop.egg-info/top_level.txt