Metadata-Version: 1.1
Name: xmlsec-aop
Version: 0.6.0.2
Summary: Python bindings for the XML Security Library.
Home-page: https://github.com/aop/python-xmlsec
Author: Ryan Leckey
Author-email: support@mehcode.com
License: UNKNOWN
Platform: UNKNOWN
Classifier: Development Status :: 3 - Alpha
Classifier: Intended Audience :: Developers
Classifier: Intended Audience :: System Administrators
Classifier: License :: OSI Approved :: MIT License
Classifier: Operating System :: OS Independent
Classifier: Programming Language :: Cython
Classifier: Programming Language :: Python :: 2.7
Classifier: Programming Language :: Python :: 3
Classifier: Programming Language :: Python :: 3.3
Classifier: Programming Language :: Python :: 3.4
Classifier: Topic :: Text Processing :: Markup :: XML
